lab_instruments/__init__.py
lab_instruments/serial_instrument.py
lab_instruments-0.0.2.dist-info/LICENSE
lab_instruments-0.0.2.dist-info/METADATA
lab_instruments-0.0.2.dist-info/WHEEL
lab_instruments-0.0.2.dist-info/top_level.txt
lab_instruments-0.0.2.dist-info/RECORD
